Workbook

Sheet CATÁLOGO
H1: =SUM(H5:H31) -> 8637.64 | I1: =SUM(I5:I31) -> 13131 | J1: =SUM(J5:J31) -> 4493.36 | K1: =J1/I1 -> 0.34219481
B4: ARTÍCULO | C4: COSTO | D4: PRECIO SUGERIDO | E4: PRECIO FINAL | F4: UTILIDAD | G4: CANTIDAD | H4: COSTO TOTAL | I4: VENTA TOTAL | J4: UTILIDAD TOTAL
B5: Termo La Bella y la Bestia | C5: 432.2 | D5: =C5*(1+(VLOOKUP(C5,'TABLA DE PRECIOS'!B:D,3,1))) -> 626.69 | E5: 649 | F5: =E5-C5 -> 216.8 | G5: 1 | H5: =G5*C5 -> 432.2 | I5: =G5*E5 -> 649 | J5: =G5*F5 -> 216.8
B6: Vela Harry Potter | C6: 432.03 | D6: =C6*(1+(VLOOKUP(C6,'TABLA DE PRECIOS'!B:D,3,1))) -> 626.4435 | E6: 649 | F6: =E6-C6 -> 216.97 | G6: 1 | H6: =G6*C6 -> 432.03 | I6: =G6*E6 -> 649 | J6: =G6*F6 -> 216.97
B7: Gorra I love sports | C7: 483.89 | D7: =C7*(1+(VLOOKUP(C7,'TABLA DE PRECIOS'!B:D,3,1))) -> 701.6405 | E7: 649 | F7: =E7-C7 -> 165.11 | G7: 1 | H7: =G7*C7 -> 483.89 | I7: =G7*E7 -> 649 | J7: =G7*F7 -> 165.11
B8: Separador magnético | C8: 46 | D8: =C8*(1+(VLOOKUP(C8,'TABLA DE PRECIOS'!B:D,3,1))) -> 138 | E8: 79 | F8: =E8-C8 -> 33 | G8: 4 | H8: =G8*C8 -> 184 | I8: =G8*E8 -> 316 | J8: =G8*F8 -> 132
B9: Reading journal | C9: 553.22 | D9: =C9*(1+(VLOOKUP(C9,'TABLA DE PRECIOS'!B:D,3,1))) -> 802.169 | E9: 799 | F9: =E9-C9 -> 245.78 | G9: 1 | H9: =G9*C9 -> 553.22 | I9: =G9*E9 -> 799 | J9: =G9*F9 -> 245.78
B10: Book cover | C10: 414.91 | D10: =C10*(1+(VLOOKUP(C10,'TABLA DE PRECIOS'!B:D,3,1))) -> 601.6195 | E10: 499 | F10: =E10-C10 -> 84.09 | G10: 2 | H10: =G10*C10 -> 829.82 | I10: =G10*E10 -> 998 | J10: =G10*F10 -> 168.18
B11: Cobija con diseño de libros | C11: 604.91 | D11: =C11*(1+(VLOOKUP(C11,'TABLA DE PRECIOS'!B:D,3,1))) -> 877.1195 | E11: 999 | F11: =E11-C11 -> 394.09 | G11: 1 | H11: =G11*C11 -> 604.91 | I11: =G11*E11 -> 999 | J11: =G11*F11 -> 394.09
B12: Vela Orgullo y Prejuicio | C12: 345.59 | D12: =C12*(1+(VLOOKUP(C12,'TABLA DE PRECIOS'!B:D,3,1))) -> 501.1055 | E12: 549 | F12: =E12-C12 -> 203.41 | G12: 0 | H12: =G12*C12 -> 0 | I12: =G12*E12 -> 0 | J12: =G12*F12 -> 0
B13: Journal bordado (verde) | C13: 553.22 | D13: =C13*(1+(VLOOKUP(C13,'TABLA DE PRECIOS'!B:D,3,1))) -> 802.169 | E13: 799 | F13: =E13-C13 -> 245.78 | G13: 1 | H13: =G13*C13 -> 553.22 | I13: =G13*E13 -> 799 | J13: =G13*F13 -> 245.78
B14: Tote bag Orgullo y Prejuicio | C14: 432.2 | D14: =C14*(1+(VLOOKUP(C14,'TABLA DE PRECIOS'!B:D,3,1))) -> 626.69 | E14: 649 | F14: =E14-C14 -> 216.8 | G14: 1 | H14: =G14*C14 -> 432.2 | I14: =G14*E14 -> 649 | J14: =G14*F14 -> 216.8
B15: Tote bag Toni Morrison | C15: 432.03 | D15: =C15*(1+(VLOOKUP(C15,'TABLA DE PRECIOS'!B:D,3,1))) -> 626.4435 | E15: 649 | F15: =E15-C15 -> 216.97 | G15: 1 | H15: =G15*C15 -> 432.03 | I15: =G15*E15 -> 649 | J15: =G15*F15 -> 216.97
B16: Tote bag I love sports romance | C16: 345.59 | D16: =C16*(1+(VLOOKUP(C16,'TABLA DE PRECIOS'!B:D,3,1))) -> 501.1055 | E16: 649 | F16: =E16-C16 -> 303.41 | G16: 1 | H16: =G16*C16 -> 345.59 | I16: =G16*E16 -> 649 | J16: =G16*F16 -> 303.41
... B31: Emma (libro) | C31: 330 | D31: =C31*(1+(VLOOKUP(C31,'TABLA DE PRECIOS'!B:D,3,1))) -> 478.5 | E31: 499 | F31: =E31-C31 -> 169 | G31: 0 | H31: =G31*C31 -> 0 | I31: =G31*E31 -> 0 | J31: =G31*F31 -> 0
B32: Tazas Costco de flores | D32: =C32*(1+(VLOOKUP(C32,'TABLA DE PRECIOS'!B:D,3,1))) -> 0 | F32: =E32-C32 -> 0 | G32: 5 | H32: =G32*C32 -> 0 | I32: =G32*E32 -> 0 | J32: =G32*F32 -> 0
B33: Separador Rifle Paper Co. | C33: 170 | D33: =C33*(1+(VLOOKUP(C33,'TABLA DE PRECIOS'!B:D,3,1))) -> 340 | E33: 340 | F33: =E33-C33 -> 170 | G33: 1 | H33: =G33*C33 -> 170 | I33: =G33*E33 -> 340 | J33: =G33*F33 -> 170
B34: Pluma Rifle Paper Co. | C34: 280 | D34: =C34*(1+(VLOOKUP(C34,'TABLA DE PRECIOS'!B:D,3,1))) -> 560 | E34: 499 | F34: =E34-C34 -> 219 | G34: 2 | H34: =G34*C34 -> 560 | I34: =G34*E34 -> 998 | J34: =G34*F34 -> 438
B35: Llavero Rifle Paper Co. | C35: 330 | D35: =C35*(1+(VLOOKUP(C35,'TABLA DE PRECIOS'!B:D,3,1))) -> 478.5 | E35: 449 | F35: =E35-C35 -> 119 | G35: 1 | H35: =G35*C35 -> 330 | I35: =G35*E35 -> 449 | J35: =G35*F35 -> 119

Sheet GASTOS
D3: COSTO TOTAL | E3: UNIDADES
B4: CAJAS DE CARTÓN
B5: STICKERS
B6: SEPARADORES
B7: POST ITS SEPARADORES
B8: PAPEL DE CHINA
B9: PAPEL DE CHINA CORTADO
B10: BOOK TRACKER
B11: BISCOFF

Sheet TABLA DE PRECIOS
B5: PRECIO MÍNIMO | C5: PRECIO MÁXIMO | D5: MARK UP
B6: 0 | C6: 100 | D6: 2
B7: 101 | C7: 300 | D7: 1
B8: 301 | C8: 800 | D8: 0.45
B9: 801 | C9: 1000 | D9: 0.4
B10: 1001 | C10: 1500 | D10: 0.35
B11: 1501 | C11: 100000000 | D11: 0.3

Sheet VENTAS ABRIL-MAYO
B5: KITS VENDIDOS | C5: PRECIO | D5: CANTIDAD | G5: PRODUCTOS INDIVIDUALES VENDIDOS | H5: PRECIO | I5: CANTIDAD
A7: 1 | B7: KIT VERDE B&N | C7: 1450 | D7: 1 | F7: 3 | G7: TOTE BAG LA BELLA Y LA BESTIA | H7: 799 | I7: 1
B8: TOTE BAG: BAG OF BOOKS | G8: CAJA DE CARTÓN
B9: VELA AROMÁTICA VERDE | G9: LIP BALM
B10: SEPARADOR MAGNÉTICO VERDE | G10: TE GOURMET
B11: LITTLE WOMEN (LIBRO) | G11: CHOCOLATE FERRERO
B12: STICKERS | G12: STICKERS
B13: POST ITS / SEPARADORES | G13: 2 SEPARADORES
B14: BOOK TRACKER
B15: 1 CAJA CARTÓN | F15: 4 | G15: BOOK JOURNAL BEIGE | H15: 799 | I15: 1
B16: 1 BOLSA DE PAPEL CHINA | G16: CAJA DE CARTÓN
B17: GALLETAS BISCOFF | G17: LIP BALM
G18: TE GOURMET
G19: CHOCOLATE FERRERO
A20: 2 | B20: KIT ROSA B&N | C20: 1450 | D20: 1 | G20: STICKERS
B21: TOTE BAG: BAG OF BOOKS | G21: 2 SEPARADORES
B22: VELA AROMÁTICA ROSA
B23: SEPARADOR MAGNÉTICO ROSA | F23: 5 | G23: VELA ROSA ORGULLO Y PREJUICIO | H23: 550 | I23: 1
B24: EMMA (LIBRO) | G24: CAJA DE CARTÓN
B25: STICKERS | G25: LIP BALM
B26: POST ITS / SEPARADORES | G26: TE GOURMET
B27: BOOK TRACKER | G27: CHOCOLATE FERRERO
B28: 1 CAJA CARTÓN | G28: STICKERS
B29: 1 BOLSA DE PAPEL CHINA | G29: 2 SEPARADORES
B30: GALLETAS BISCOFF
A37: TOTAL | B37: =C7+H7+H15+H23+C20 -> 5048
